Workbook

Sheet Premissas
A1: Premissas
A2: Células em azul são entradas editáveis; todas as outras abas recalculam a partir daqui. ⚠️ = estimativa que não consta nos documentos do projeto.
A4: Premissa | B4: Valor | C4: Fonte
A5: Ticket médio por Corrida (Preço fechado) | B5: 300 | C5: unit-economics.md
A6: Comissão da plataforma | B6: 0.2 | C6: ADR-0003 / CONTEXT.md
A7: Processamento de pagamento (% do ticket) | B7: 0.03 | C7: ADR-0004
A8: Subsídio de disponibilidade por Corrida (meses 1–6) | B8: 25 | C8: unit-economics.md
A9: Duração do MVP (meses) | B9: 6 | C9: unit-economics.md
A10: Custos fixos mensais, cenário A (sem pró-labore) | B10: 5500 | C10: unit-economics.md
A11: Custos fixos mensais, cenário B (com 2 contratações) | B11: 18000 | C11: unit-economics.md
A12: Câmbio (R$ por US$) ⚠️ | B12: 5.5 | C12: Estimativa; atualizar na cotação do dia
A13: Códigos de login enviados por mês ⚠️ | B13: 800 | C13: Estimativa
A14: Custo por código WhatsApp/SMS (R$) ⚠️ | B14: 0.3 | C14: Estimativa
A15: Nº de Frotas âncora | B15: 3 | C15: ADR-0006
A16: Meses de subsídio às Frotas âncora | B16: 3 | C16: ADR-0006 (90 dias)
... A22: Hospedagem do bot de mensagens, R$/mês ⚠️ | B22: 0 | C22: 0 se rodar em servidor/n8n já existente; ~R$ 30 em VPS pequena

Sheet Investimento
A1: Investimento do MVP (6 meses)
A2: Fonte: unit-economics.md. Desenvolvimento feito pelos fundadores: custo de oportunidade, não caixa.
A4: Item | B4: Grupo | C4: Valor (R$) | D4: % do total | E4: Cenário enxuto (R$)
A5: Desenvolvimento do PWA (3 superfícies) | B5: Desenvolvimento | C5: 0 | D5: =C5/$C$13 -> 0 | E5: =C5 -> 0
A6: Infraestrutura, mapas, hospedagem e ferramentas | B6: Operação e oferta | C6: 7000 | D6: =C6/$C$13 -> 0.10769231 | E6: =Stack!C14 -> 260
A7: Constituição da empresa e contabilidade | B7: Conformidade | C7: 5000 | D7: =C7/$C$13 -> 0.076923077 | E7: =C7 -> 5000
A8: Jurídico (contrato, termos de uso, privacidade) | B8: Conformidade | C8: 6000 | D8: =C8/$C$13 -> 0.092307692 | E8: =C8 -> 6000
A9: Seguro de RC da operação | B9: Conformidade | C9: 9000 | D9: =C9/$C$13 -> 0.13846154 | E9: =C9 -> 9000
A10: Subsídio às Frotas âncora (90 dias) | B10: Operação e oferta | C10: 18000 | D10: =C10/$C$13 -> 0.27692308 | E10: =C10 -> 18000
A11: Marketing de aquisição (teste de canal) | B11: Aquisição | C11: 12000 | D11: =C11/$C$13 -> 0.18461538 | E11: =C11 -> 12000
A12: Reserva de contingência | B12: Contingência | C12: 8000 | D12: =C12/$C$13 -> 0.12307692 | E12: =C12 -> 8000
A13: Total | C13: =SUM(C5:C12) -> 65000 | D13: =SUM(D5:D12) -> 1 | E13: =SUM(E5:E12) -> 58260
A15: Custo médio mensal (total ÷ meses do MVP) | C15: =C13/Premissas!B9 -> 10833.333
A16: Subsídio por Frota por mês | C16: =C10/Premissas!B15/Premissas!B16 -> 2000
A17: Economia do cenário enxuto vs. base | E17: =C13-E13 -> 6740
A18: Por grupo | C18: Valor (R$) | D18: % do total
A19: Conformidade | C19: =SUMIF($B$5:$B$12,A19,$C$5:$C$12) -> 20000 | D19: =C19/$C$13 -> 0.30769231
A20: Operação e oferta | C20: =SUMIF($B$5:$B$12,A20,$C$5:$C$12) -> 25000 | D20: =C20/$C$13 -> 0.38461538
A21: Aquisição | C21: =SUMIF($B$5:$B$12,A21,$C$5:$C$12) -> 12000 | D21: =C21/$C$13 -> 0.18461538
A22: Contingência | C22: =SUMIF($B$5:$B$12,A22,$C$5:$C$12) -> 8000 | D22: =C22/$C$13 -> 0.12307692
A23: Desenvolvimento | C23: =SUMIF($B$5:$B$12,A23,$C$5:$C$12) -> 0 | D23: =C23/$C$13 -> 0

Sheet Stack
A1: Stack técnica e custo mensal de ferramentas
A2: Stack do ADR-0008. Preços ⚠️ estimados a partir de tabelas públicas; confirmar com cotação.
A4: Camada | B4: Tecnologia | C4: Enxuto/mês (R$): planos grátis + bot próprio | D4: Escala/mês (R$): planos pagos + API oficial | E4: Observação
A5: Front-end (3 PWAs) | B5: React, Vite, vite-plugin-pwa, TanStack Query | C5: 0 | D5: 0 | E5: Open source
A6: Hospedagem | B6: Vercel | C6: 0 | D6: =20*Premissas!B12 -> 110 | E6: Enxuto: Hobby (grátis; uso não comercial). Escala: Pro, US$ 20
A7: Back-end | B7: Supabase (Postgres+PostGIS, Auth, Storage, Realtime) | C7: 0 | D7: =25*Premissas!B12 -> 137.5 | E7: Enxuto: Free (pausa por inatividade, sem backup). Escala: Pro, US$ 25
A8: Mapas, geocoding e rotas | B8: Mapbox | C8: 0 | D8: 0 | E8: Cota gratuita; cobra por uso acima dela
A9: Login por telefone (código por WhatsApp) | B9: Enxuto: número próprio + bot (ex.: n8n). Escala: API oficial do WhatsApp | C9: =Premissas!B21+Premissas!B22 -> 40 | D9: =Premissas!B13*Premissas!B14 -> 240 | E9: Enxuto: chip + hospedagem do bot. Escala: códigos/mês × custo por código. Bot não oficial pode ser banido pelo WhatsApp
A10: Domínio .com.br | B10: Registro.br | C10: =40/12 -> 3.3333333 | D10: =40/12 -> 3.3333333 | E10: R$ 40 por ano ÷ 12 (⚠️ estimativa)
A11: Testes, repositório e CI | B11: Vitest, Playwright, GitHub | C11: 0 | D11: 0 | E11: Gratuitos
A12: Pagamento (PSP com split) | B12: Pagar.me / Asaas / Iugu / Mercado Pago | C12: 0 | D12: 0 | E12: Sem mensalidade; ~3% por Corrida (ver aba Unit economics)
A13: Total por mês | C13: =SUM(C5:C12) -> 43.333333 | D13: =SUM(D5:D12) -> 490.83333
A14: Total no MVP (× meses) | C14: =C13*Premissas!B9 -> 260 | D14: =D13*Premissas!B9 -> 2945
A15: Verba prevista para infraestrutura | C15: =Investimento!C6 -> 7000 | D15: =Investimento!C6 -> 7000
A16: Folga da verba | C16: =C15-C14 -> 6740 | D16: =D15-D14 -> 4055

Sheet Normas
A1: Adequação a normas: custos iniciais
A2: Bases: ADR-0001, 0004, 0007 e pesquisa regulatória. Não é parecer jurídico; validar com advogado.
A4: Exigência | B4: Base | C4: Quem paga | D4: Mínimo (R$) | E4: Máximo (R$) | F4: Observação
A5: Constituição da empresa e contabilidade (6 meses) | B5: Rede Sim-DF, Junta, alvará | C5: Plataforma | D5: =Investimento!C7 -> 5000 | E5: =Investimento!C7 -> 5000 | F5: Já no orçamento
A6: Jurídico: contrato, termos de uso, LGPD | B6: CDC, LGPD | C6: Plataforma | D6: =Investimento!C8 -> 6000 | E6: =Investimento!C8 -> 6000 | F6: Já no orçamento
A7: Seguro de RC da operação (6 meses) | B7: ADR-0007 | C7: Plataforma | D7: =Investimento!C9 -> 9000 | E7: =Investimento!C9 -> 9000 | F7: Já no orçamento
A8: Apólice de avaria, Guinchei cossegurado | B8: ADR-0007; CDC arts. 7º, 14, 25 | C8: Cada Frota | D8: 0 | E8: 0 | F8: Custo da Frota; gera atrito no cadastro
A9: Verificação manual da Frota (CNPJ, DETRAN, CNH, apólice) | B9: ADR-0007, Invariante 3 | C9: Plataforma | D9: 0 | E9: 0 | F9: Sem desembolso; custa horas da operação
A10: PSP com split, sem custódia | B10: ADR-0004; Res. BCB 80/2021 | C10: Plataforma | D10: 0 | E10: 0 | F10: Evita autorização do BC (capital mín. R$ 2 mi)
A11: Corridas só no DF | B11: ADR-0001 | C11: Plataforma | D11: 0 | E11: 0 | F11: Evita regime ANTT/RNTRC/CT-e
A12: Registro da marca no INPI ⚠️ | B12: Não consta no repositório | C12: Plataforma | D12: 400 | E12: 700 | F12: Estimativa; sairia da contingência
A13: Total pago pela plataforma | D13: =SUMIF($C$5:$C$12,"Plataforma",D5:D12) -> 20400 | E13: =SUMIF($C$5:$C$12,"Plataforma",E5:E12) -> 20700
A14: Contabilidade mensal ⚠️ (já inclusa na linha de constituição) | C14: Plataforma | D14: 400 | E14: 800 | F14: Estimativa por mês

Sheet Unit economics
A1: Margem por Corrida
A2: Cálculo a partir das premissas; mudar o ticket ou a comissão atualiza todo o modelo.
A4: Linha | B4: Valor (R$) | C4: Nota
A5: Ticket médio (Preço fechado) | B5: =Premissas!B5 -> 300 | C5: Pago pelo Cliente
A6: Comissão da plataforma | B6: =B5*Premissas!B6 -> 60 | C6: Receita bruta de intermediação
A7: Repasse ao Guincheiro | B7: =B5-B6 -> 240 | C7: Passa pelo PSP; não é custo
A8: Processamento de pagamento | B8: =-B5*Premissas!B7 -> -9 | C8: ~3% do ticket
A9: Líquido por Corrida (antes de opex) | B9: =B6+B8 -> 51
A10: Subsídio de disponibilidade (meses 1–6) | B10: =-Premissas!B8 -> -25 | C10: Frotas âncora
A11: Contribuição inicial (com subsídio) | B11: =B9+B10 -> 26 | C11: Meses 1–6
A12: Contribuição na maturidade | B12: =B9-Premissas!B20 -> 48 | C12: Sem subsídio; desconta outros custos variáveis (suporte/Disputa)

Sheet Equilíbrio e projeção
A1: Ponto de equilíbrio e projeção de volume
A2: Equilíbrio = custos fixos ÷ margem de contribuição por Corrida, arredondado para cima.
A4: Cenário | B4: Custos fixos/mês | C4: Margem/Corrida | D4: Corridas/mês p/ equilíbrio
A5: A · início (com subsídio) | B5: =Premissas!B10 -> 5500 | C5: ='Unit economics'!B11 -> 26 | D5: =IF(C5>0,ROUNDUP(B5/C5,0),0) -> 212
A6: A · maturidade | B6: =Premissas!B10 -> 5500 | C6: ='Unit economics'!B12 -> 48 | D6: =IF(C6>0,ROUNDUP(B6/C6,0),0) -> 115
A7: B · maturidade (com equipe) | B7: =Premissas!B11 -> 18000 | C7: ='Unit economics'!B12 -> 48 | D7: =IF(C7>0,ROUNDUP(B7/C7,0),0) -> 375
A10: Projeção | B10: Mínimo | C10: Ponto médio | D10: Máximo
A11: Mês 3: Corridas/mês | B11: =Premissas!B17 -> 300 | C11: =AVERAGE(B11,D11) -> 400 | D11: =Premissas!B18 -> 500
A12: Mês 3: GMV/mês | B12: =B11*Premissas!$B$5 -> 90000 | C12: =C11*Premissas!$B$5 -> 120000 | D12: =D11*Premissas!$B$5 -> 150000
A13: Mês 3: Receita de intermediação/mês | B13: =B12*Premissas!$B$6 -> 18000 | C13: =C12*Premissas!$B$6 -> 24000 | D13: =D12*Premissas!$B$6 -> 30000
A15: Mês 12 | B15: Valor
A16: Corridas/mês | B16: =Premissas!B19 -> 1500
A17: GMV/mês | B17: =B16*Premissas!B5 -> 450000
A18: Receita de intermediação/mês | B18: =B17*Premissas!B6 -> 90000
A19: Margem de contribuição/mês (maturidade) | B19: =B16*'Unit economics'!B12 -> 72000
A20: Margem − fixos do cenário B | B20: =B19-Premissas!B11 -> 54000

Sheet Receitas
A1: Fontes de receita
A2: Receitas planejadas por fase. Fontes de capital estão listadas à parte: não são receita.
A4: Fonte | B4: Fase | C4: Modelo | D4: Valor por Corrida (R$)
A5: Comissão de 20% por Corrida | B5: 1 · MVP | C5: Sem custo de entrada para o Guincheiro | D5: ='Unit economics'!B6 -> 60
A6: Assistência completa (bateria, pneu, pane seca, chaveiro) | B6: 2 | C6: Mesma comissão, mais categorias | D6: a definir
A7: Contratos B2B2C com seguradoras e assistências 24h | B7: 3 | C7: Receita recorrente | D7: a definir
A8: Novas praças (Goiânia e entorno) | B8: 3 | C8: Mesmo modelo, mais volume | D8: a definir
A10: Fontes de capital (não são receita)
A11: Bootstrapping dos fundadores
A12: Incubação e aceleração universitária (UCB)
A13: Editais: FAP-DF, FINEP, Sebrae
A14: Investimento anjo e pré-seed (após validar o MVP)
